akcompress
